rxls/__init__.py
rxls/biff.py
rxls/biff_enum.py
rxls/biff_recs.py
rxls/cell.py
rxls/constants.py
rxls/core.py
rxls/rels.py
rxls/series.py
rxls/chunk/__init__.py
rxls/chunk/arrow.py
rxls/chunk/casts.py
rxls/chunk/chunk.py
rxls/reader/__init__.py
rxls/reader/common.py
rxls/reader/xlsb.py
rxls/reader/xlsx.py
rxls-0.2.2.dist-info/LICENSE
rxls-0.2.2.dist-info/METADATA
rxls-0.2.2.dist-info/WHEEL
rxls-0.2.2.dist-info/top_level.txt
rxls-0.2.2.dist-info/RECORD
