Metadata-Version: 2.1
Name: rxls
Version: 0.2.2
Summary: Reading both XLSX and XLSB files, fast and memory-safe, into PyArrow.
Author-email: SaelKimberly <sael.kimberly@yandex.ru>
License: MIT
Project-URL: Homepage, https://github.com/SaelKimberly/rxls
Project-URL: Documentation, https://github.com/SaelKimberly/rxls
Project-URL: Repository, https://github.com/SaelKimberly/rxls.git
Project-URL: Issues, https://github.com/SaelKimberly/rxls/issues
Requires-Python: >=3.8
License-File: LICENSE
Requires-Dist: recordclass >=0.21.1
Requires-Dist: numpy >=1.24.4
Requires-Dist: pyarrow >=14.0.2
Requires-Dist: typing-extensions >=4.9.0
Provides-Extra: benchmarks
Requires-Dist: notebook >=7.0.6 ; extra == 'benchmarks'
Requires-Dist: xlsx2csv >=0.8.2 ; extra == 'benchmarks'
Requires-Dist: lxml >=5.1.0 ; extra == 'benchmarks'
Requires-Dist: openpyxl >=3.1.2 ; extra == 'benchmarks'
Requires-Dist: pyxlsb >=1.0.10 ; extra == 'benchmarks'
Requires-Dist: python-calamine >=0.1.7 ; extra == 'benchmarks'
Requires-Dist: memory-profiler >=0.61.0 ; extra == 'benchmarks'
Requires-Dist: py-cpuinfo >=9.0.0 ; extra == 'benchmarks'
Requires-Dist: matplotlib >=3.7.4 ; extra == 'benchmarks'
Provides-Extra: performance
Requires-Dist: numba >=0.58.1 ; extra == 'performance'
Requires-Dist: tbb >=2021.11.0 ; extra == 'performance'
Provides-Extra: tests
Requires-Dist: pytest >=7.4.4 ; extra == 'tests'
Provides-Extra: ts_extended
Requires-Dist: polars >=0.20.4 ; extra == 'ts_extended'
